{
    "__comment": "Designed by Wiiv with Cubik Studio - https://cubik.studio",
    "ambientocclusion": true,
    "parent": "block/block",
    "textures": {
        "particle": "astralsorcery:block/fountain_prime_base",
        "texture": "astralsorcery:block/fountain_prime_ore",
        "texture1": "astralsorcery:block/fountain_prime_base",
        "texture2": "astralsorcery:block/fountain_prime_fitting"
    },
    "elements": [
        {
            "__comment": "Box1",
            "from": [ 7, 0, 0.01 ],
            "to": [ 9, 4, 4.01 ],
            "faces": {
                "down": { "uv": [ 2, 12, 4, 16 ], "texture": "#texture2" },
                "up": { "uv": [ 2, 12, 4, 16 ], "texture": "#texture2" },
                "north": { "uv": [ 2, 12, 4, 16 ], "texture": "#texture2" },
                "south": { "uv": [ 2, 12, 4, 16 ], "texture": "#texture2" },
                "west": { "uv": [ 4, 12, 8, 16 ], "texture": "#texture2" },
                "east": { "uv": [ 4, 12, 8, 16 ], "texture": "#texture2" }
            }
        },
        {
            "__comment": "Box1",
            "from": [ 6.0002, 1.9993, 2 ],
            "to": [ 10.0002, 11.9993, 4 ],
            "faces": {
                "down": { "uv": [ 4, 10, 8, 12 ], "texture": "#texture2" },
                "up": { "uv": [ 4, 10, 8, 12 ], "texture": "#texture2" },
                "north": { "uv": [ 4, 0, 8, 10 ], "texture": "#texture2" },
                "south": { "uv": [ 4, 0, 8, 10 ], "texture": "#texture2" },
                "west": { "uv": [ 8, 0, 10, 10 ], "texture": "#texture2" },
                "east": { "uv": [ 8, 0, 10, 10 ], "texture": "#texture2" }
            }
        },
        {
            "__comment": "Box1",
            "from": [ 6.0002, 1.9993, 12 ],
            "to": [ 10.0002, 11.9993, 14 ],
            "faces": {
                "down": { "uv": [ 4, 10, 8, 12 ], "texture": "#texture2" },
                "up": { "uv": [ 4, 10, 8, 12 ], "texture": "#texture2" },
                "north": { "uv": [ 4, 0, 8, 10 ], "texture": "#texture2" },
                "south": { "uv": [ 4, 0, 8, 10 ], "texture": "#texture2" },
                "west": { "uv": [ 8, 0, 10, 10 ], "texture": "#texture2" },
                "east": { "uv": [ 8, 0, 10, 10 ], "texture": "#texture2" }
            }
        },
        {
            "__comment": "Box1",
            "from": [ 10, 10, 6.9995 ],
            "to": [ 14, 14, 8.9995 ],
            "faces": {
                "down": { "uv": [ 4, 10, 8, 12 ], "texture": "#texture2" },
                "up": { "uv": [ 4, 10, 8, 12 ], "texture": "#texture2" },
                "north": { "uv": [ 4, 12, 8, 16 ], "texture": "#texture2" },
                "south": { "uv": [ 4, 12, 8, 16 ], "texture": "#texture2" },
                "west": { "uv": [ 2, 12, 4, 16 ], "texture": "#texture2" },
                "east": { "uv": [ 2, 12, 4, 16 ], "texture": "#texture2" }
            }
        },
        {
            "__comment": "Box1",
            "from": [ 7, 0, 12.01 ],
            "to": [ 9, 4, 16.01 ],
            "faces": {
                "down": { "uv": [ 2, 12, 4, 16 ], "texture": "#texture2" },
                "up": { "uv": [ 2, 12, 4, 16 ], "texture": "#texture2" },
                "north": { "uv": [ 2, 12, 4, 16 ], "texture": "#texture2" },
                "south": { "uv": [ 2, 12, 4, 16 ], "texture": "#texture2" },
                "west": { "uv": [ 4, 12, 8, 16 ], "texture": "#texture2" },
                "east": { "uv": [ 4, 12, 8, 16 ], "texture": "#texture2" }
            }
        },
        {
            "__comment": "Box1",
            "from": [ 7, 10, 12.01 ],
            "to": [ 9, 14, 16.01 ],
            "faces": {
                "down": { "uv": [ 2, 12, 4, 16 ], "texture": "#texture2" },
                "up": { "uv": [ 2, 12, 4, 16 ], "texture": "#texture2" },
                "north": { "uv": [ 2, 12, 4, 16 ], "texture": "#texture2" },
                "south": { "uv": [ 2, 12, 4, 16 ], "texture": "#texture2" },
                "west": { "uv": [ 4, 12, 8, 16 ], "texture": "#texture2" },
                "east": { "uv": [ 4, 12, 8, 16 ], "texture": "#texture2" }
            }
        },
        {
            "__comment": "Box1",
            "from": [ 7, 10, 0.01 ],
            "to": [ 9, 14, 4.01 ],
            "faces": {
                "down": { "uv": [ 2, 12, 4, 16 ], "texture": "#texture2" },
                "up": { "uv": [ 2, 12, 4, 16 ], "texture": "#texture2" },
                "north": { "uv": [ 2, 12, 4, 16 ], "texture": "#texture2" },
                "south": { "uv": [ 2, 12, 4, 16 ], "texture": "#texture2" },
                "west": { "uv": [ 4, 12, 8, 16 ], "texture": "#texture2" },
                "east": { "uv": [ 4, 12, 8, 16 ], "texture": "#texture2" }
            }
        },
        {
            "__comment": "Box1",
            "from": [ 2, 10, 6.9995 ],
            "to": [ 6, 14, 8.9995 ],
            "faces": {
                "down": { "uv": [ 4, 10, 8, 12 ], "texture": "#texture2" },
                "up": { "uv": [ 4, 10, 8, 12 ], "texture": "#texture2" },
                "north": { "uv": [ 4, 12, 8, 16 ], "texture": "#texture2" },
                "south": { "uv": [ 4, 12, 8, 16 ], "texture": "#texture2" },
                "west": { "uv": [ 2, 12, 4, 16 ], "texture": "#texture2" },
                "east": { "uv": [ 2, 12, 4, 16 ], "texture": "#texture2" }
            }
        },
        {
            "__comment": "Box1",
            "from": [ 4, 12, 4 ],
            "to": [ 12, 16, 12 ],
            "faces": {
                "down": { "uv": [ 0, 0, 8, 8 ], "texture": "#texture1" },
                "up": { "uv": [ 8, 0, 16, 8 ], "texture": "#texture1" },
                "north": { "uv": [ 0, 8, 8, 12 ], "texture": "#texture1" },
                "south": { "uv": [ 0, 8, 8, 12 ], "texture": "#texture1" },
                "west": { "uv": [ 0, 8, 8, 12 ], "texture": "#texture1" },
                "east": { "uv": [ 0, 8, 8, 12 ], "texture": "#texture1" }
            }
        },
        {
            "__comment": "Box1",
            "from": [ 7.0001, -10.0012, 5 ],
            "to": [ 9.000099, 5.9988, 7 ],
            "faces": {
                "down": { "uv": [ 2, 0, 4, 2 ], "texture": "#texture" },
                "up": { "uv": [ 2, 0, 4, 2 ], "texture": "#texture" },
                "north": { "uv": [ 0, 0, 2, 16 ], "texture": "#texture" },
                "south": { "uv": [ 0, 0, 2, 16 ], "texture": "#texture" },
                "west": { "uv": [ 0, 0, 2, 16 ], "texture": "#texture" },
                "east": { "uv": [ 0, 0, 2, 16 ], "texture": "#texture" }
            }
        },
        {
            "__comment": "Box1",
            "from": [ 7, 6, 0 ],
            "to": [ 9, 8, 2 ],
            "faces": {
                "down": { "uv": [ 2, 0, 4, 2 ], "texture": "#texture" },
                "up": { "uv": [ 2, 0, 4, 2 ], "texture": "#texture" },
                "north": { "uv": [ 2, 0, 4, 2 ], "texture": "#texture" },
                "south": { "uv": [ 2, 0, 4, 2 ], "texture": "#texture" },
                "west": { "uv": [ 2, 0, 4, 2 ], "texture": "#texture" },
                "east": { "uv": [ 2, 0, 4, 2 ], "texture": "#texture" }
            }
        },
        {
            "__comment": "Box1",
            "from": [ 7, 9, 7 ],
            "to": [ 9, 11, 9 ],
            "faces": {
                "down": { "uv": [ 2, 2, 4, 4 ], "texture": "#texture" },
                "up": { "uv": [ 2, 2, 4, 4 ], "texture": "#texture" },
                "north": { "uv": [ 2, 2, 4, 4 ], "texture": "#texture" },
                "south": { "uv": [ 2, 2, 4, 4 ], "texture": "#texture" },
                "west": { "uv": [ 2, 2, 4, 4 ], "texture": "#texture" },
                "east": { "uv": [ 2, 2, 4, 4 ], "texture": "#texture" }
            }
        },
        {
            "__comment": "Box1",
            "from": [ 4, 0, 7 ],
            "to": [ 6, 8, 9 ],
            "faces": {
                "down": { "uv": [ 2, 0, 4, 2 ], "texture": "#texture" },
                "up": { "uv": [ 2, 0, 4, 2 ], "texture": "#texture" },
                "north": { "uv": [ 2, 4, 4, 12 ], "texture": "#texture" },
                "south": { "uv": [ 2, 4, 4, 12 ], "texture": "#texture" },
                "west": { "uv": [ 2, 4, 4, 12 ], "texture": "#texture" },
                "east": { "uv": [ 2, 4, 4, 12 ], "texture": "#texture" }
            }
        },
        {
            "__comment": "Box1",
            "from": [ 7.0001, -10.0012, 9 ],
            "to": [ 9.000099, 5.9988, 11 ],
            "faces": {
                "down": { "uv": [ 2, 0, 4, 2 ], "texture": "#texture" },
                "up": { "uv": [ 2, 0, 4, 2 ], "texture": "#texture" },
                "north": { "uv": [ 0, 0, 2, 16 ], "texture": "#texture" },
                "south": { "uv": [ 0, 0, 2, 16 ], "texture": "#texture" },
                "west": { "uv": [ 0, 0, 2, 16 ], "texture": "#texture" },
                "east": { "uv": [ 0, 0, 2, 16 ], "texture": "#texture" }
            }
        },
        {
            "__comment": "Box1",
            "from": [ 7, 6, 14 ],
            "to": [ 9, 8, 16 ],
            "faces": {
                "down": { "uv": [ 2, 0, 4, 2 ], "texture": "#texture" },
                "up": { "uv": [ 2, 0, 4, 2 ], "texture": "#texture" },
                "north": { "uv": [ 2, 0, 4, 2 ], "texture": "#texture" },
                "south": { "uv": [ 2, 0, 4, 2 ], "texture": "#texture" },
                "west": { "uv": [ 2, 0, 4, 2 ], "texture": "#texture" },
                "east": { "uv": [ 2, 0, 4, 2 ], "texture": "#texture" }
            }
        },
        {
            "__comment": "Box1",
            "from": [ 10, 0, 7 ],
            "to": [ 12, 8, 9 ],
            "faces": {
                "down": { "uv": [ 2, 0, 4, 2 ], "texture": "#texture" },
                "up": { "uv": [ 2, 0, 4, 2 ], "texture": "#texture" },
                "north": { "uv": [ 2, 4, 4, 12 ], "texture": "#texture" },
                "south": { "uv": [ 2, 4, 4, 12 ], "texture": "#texture" },
                "west": { "uv": [ 2, 4, 4, 12 ], "texture": "#texture" },
                "east": { "uv": [ 2, 4, 4, 12 ], "texture": "#texture" }
            }
        }
    ],
    "display": {
        "gui": {
            "rotation":  [ 30, 225, 0 ],
            "translation":  [ 0, 1.625, 0 ],
            "scale":  [ 0.625, 0.625, 0.625 ]
        }
    }
}